smspdu/__init__.py
smspdu/__main__.py
smspdu/codecs.py
smspdu/easy.py
smspdu/elements.py
smspdu/fields.py
smspdu/gsm0338.py
smspdu/pdu.py
smspdu/smspdu.py
smspdu/t39.py
pdusms-1.0.dist-info/LICENSE
pdusms-1.0.dist-info/METADATA
pdusms-1.0.dist-info/WHEEL
pdusms-1.0.dist-info/top_level.txt
pdusms-1.0.dist-info/RECORD
