Metadata-Version: 2.1
Name: pdusms
Version: 1.0
Summary: PDU Converter: SMS PDU encoding and decoding, including GSM-0338 character set, support Python 3
Home-page: http://pypi.python.org/pypi/smspdu
Author: Tran Tu Quang
Author-email: tuquangtran123@gmail.com
License: UNKNOWN
Platform: UNKNOWN
Classifier: Intended Audience :: Developers
Classifier: Programming Language :: Python :: 3
Classifier: Topic :: Software Development :: Libraries :: Python Modules
Classifier: License :: OSI Approved :: BSD License
Requires-Python: >=3.6
License-File: LICENSE
